tracer/__init__.py
tracer/__main__.py
tracer/json_encoder.py
tracer/json_tracer.py
json_tracer-0.6.0.dist-info/LICENSE
json_tracer-0.6.0.dist-info/METADATA
json_tracer-0.6.0.dist-info/WHEEL
json_tracer-0.6.0.dist-info/entry_points.txt
json_tracer-0.6.0.dist-info/top_level.txt
json_tracer-0.6.0.dist-info/RECORD
