Metadata-Version: 2.1
Name: json-tracer
Version: 0.6.0
Summary: Generate json traces from a python script
Author-email: Dodona <dodona@ugent.be>
License: MIT License
Project-URL: Homepage, https://github.com/dodona-edu/trace-generator
Keywords: debug,trace,json
Classifier: License :: OSI Approved :: MIT License
Classifier: Programming Language :: Python
Classifier: Programming Language :: Python :: 3
Requires-Python: >=3.11
License-File: LICENSE
Provides-Extra: dev
